[
  {
    "program_id": "nc-smart-saver-heat-pump",
    "name": "Smart $aver Heat Pump Rebate",
    "source_program_id": null,
    "eligible_upgrades": [
      "heat_pump"
    ],
    "amount_rule": {
      "amount_type": "rebate",
      "amount_flat": 1000.0,
      "amount_percent": null,
      "annual_cap": null,
      "lifetime_cap": null,
      "per_unit_rate": null,
      "per_unit_basis": null,
      "min_project_cost": null
    },
    "cap_category": null,
    "resets_annually": false,
    "available_from_year": null,
    "expires_year": null,
    "step_down_schedule": null,
    "claim_timing": "point_of_sale",
    "income_tier": null,
    "income_max_absolute": null,
    "income_max_ami_percent": null,
    "tax_liability_required": false,
    "stackable": true,
    "subsidy_basis_reduction": true,
    "exclusive_with": [],
    "ownership_required": true,
    "primary_residence_required": true,
    "home_type_eligible": [
      "single_family"
    ],
    "equipment_certification": null,
    "contractor_required": true,
    "energy_audit_required": false,
    "program_status": "active",
    "availability_type": null,
    "data_confidence": "high",
    "last_verified_date": null,
    "geographic_scope": "state",
    "state": "nc",
    "utility_territory": "Duke Energy Progress",
    "source_url": null,
    "citation_chunk_ids": [],
    "utility_notes": "Also available via Dominion Energy North Carolina \u2014 check with your utility."
  },
  {
    "program_id": "nc-smart-saver-duct-sealing",
    "name": "Smart $aver Duct Sealing Rebate",
    "source_program_id": null,
    "eligible_upgrades": [
      "duct_sealing"
    ],
    "amount_rule": {
      "amount_type": "rebate",
      "amount_flat": 500.0,
      "amount_percent": null,
      "annual_cap": null,
      "lifetime_cap": null,
      "per_unit_rate": null,
      "per_unit_basis": null,
      "min_project_cost": null
    },
    "cap_category": null,
    "resets_annually": false,
    "available_from_year": null,
    "expires_year": null,
    "step_down_schedule": null,
    "claim_timing": "point_of_sale",
    "income_tier": null,
    "income_max_absolute": null,
    "income_max_ami_percent": null,
    "tax_liability_required": false,
    "stackable": true,
    "subsidy_basis_reduction": true,
    "exclusive_with": [],
    "ownership_required": true,
    "primary_residence_required": true,
    "home_type_eligible": [
      "single_family"
    ],
    "equipment_certification": null,
    "contractor_required": true,
    "energy_audit_required": false,
    "program_status": "active",
    "availability_type": null,
    "data_confidence": "high",
    "last_verified_date": null,
    "geographic_scope": "state",
    "state": "nc",
    "utility_territory": "Duke Energy Progress",
    "source_url": null,
    "citation_chunk_ids": [],
    "utility_notes": "Also available via Dominion Energy North Carolina \u2014 check with your utility."
  },
  {
    "program_id": "nc-smart-saver-variable-speed-pool-pump",
    "name": "Smart $aver Variable-Speed Pool Pump Rebate",
    "source_program_id": null,
    "eligible_upgrades": [
      "variable_speed_pool_pump"
    ],
    "amount_rule": {
      "amount_type": "rebate",
      "amount_flat": 300.0,
      "amount_percent": null,
      "annual_cap": null,
      "lifetime_cap": null,
      "per_unit_rate": null,
      "per_unit_basis": null,
      "min_project_cost": null
    },
    "cap_category": null,
    "resets_annually": false,
    "available_from_year": null,
    "expires_year": null,
    "step_down_schedule": null,
    "claim_timing": "point_of_sale",
    "income_tier": null,
    "income_max_absolute": null,
    "income_max_ami_percent": null,
    "tax_liability_required": false,
    "stackable": true,
    "subsidy_basis_reduction": true,
    "exclusive_with": [],
    "ownership_required": true,
    "primary_residence_required": true,
    "home_type_eligible": [
      "single_family"
    ],
    "equipment_certification": null,
    "contractor_required": true,
    "energy_audit_required": false,
    "program_status": "active",
    "availability_type": null,
    "data_confidence": "high",
    "last_verified_date": null,
    "geographic_scope": "state",
    "state": "nc",
    "utility_territory": "Duke Energy Progress",
    "source_url": null,
    "citation_chunk_ids": [],
    "utility_notes": "Also available via Dominion Energy North Carolina \u2014 check with your utility."
  },
  {
    "program_id": "nc-smart-saver-energy-efficient-windows",
    "name": "Smart $aver Energy-Efficient Windows Rebate",
    "source_program_id": null,
    "eligible_upgrades": [
      "energy_efficient_windows"
    ],
    "amount_rule": {
      "amount_type": "rebate",
      "amount_flat": 500.0,
      "amount_percent": null,
      "annual_cap": null,
      "lifetime_cap": null,
      "per_unit_rate": null,
      "per_unit_basis": null,
      "min_project_cost": null
    },
    "cap_category": null,
    "resets_annually": false,
    "available_from_year": null,
    "expires_year": null,
    "step_down_schedule": null,
    "claim_timing": "point_of_sale",
    "income_tier": null,
    "income_max_absolute": null,
    "income_max_ami_percent": null,
    "tax_liability_required": false,
    "stackable": true,
    "subsidy_basis_reduction": true,
    "exclusive_with": [],
    "ownership_required": true,
    "primary_residence_required": true,
    "home_type_eligible": [
      "single_family"
    ],
    "equipment_certification": null,
    "contractor_required": true,
    "energy_audit_required": false,
    "program_status": "active",
    "availability_type": null,
    "data_confidence": "high",
    "last_verified_date": null,
    "geographic_scope": "state",
    "state": "nc",
    "utility_territory": "Duke Energy Progress",
    "source_url": null,
    "citation_chunk_ids": [],
    "utility_notes": "Also available via Dominion Energy North Carolina \u2014 check with your utility."
  },
  {
    "program_id": "nc-homes-heat_pump",
    "name": "HOMES Heat Pumps for Heating & Cooling",
    "source_program_id": null,
    "eligible_upgrades": [
      "heat_pump"
    ],
    "amount_rule": {
      "amount_type": "rebate",
      "amount_flat": null,
      "amount_percent": null,
      "annual_cap": null,
      "lifetime_cap": null,
      "per_unit_rate": null,
      "per_unit_basis": null,
      "min_project_cost": null
    },
    "cap_category": null,
    "resets_annually": false,
    "available_from_year": null,
    "expires_year": null,
    "step_down_schedule": null,
    "claim_timing": null,
    "income_tier": null,
    "income_max_absolute": null,
    "income_max_ami_percent": null,
    "tax_liability_required": false,
    "stackable": true,
    "subsidy_basis_reduction": true,
    "exclusive_with": [],
    "ownership_required": true,
    "primary_residence_required": true,
    "home_type_eligible": [
      "single_family"
    ],
    "equipment_certification": null,
    "contractor_required": true,
    "energy_audit_required": false,
    "program_status": "active",
    "availability_type": null,
    "data_confidence": "medium",
    "last_verified_date": null,
    "geographic_scope": "state",
    "state": "nc",
    "utility_territory": null,
    "source_url": null,
    "citation_chunk_ids": []
  },
  {
    "program_id": "nc-homes-heat_pump_water_heater",
    "name": "HOMES Heat Pump Water Heaters (HPWH)",
    "source_program_id": null,
    "eligible_upgrades": [
      "heat_pump_water_heater"
    ],
    "amount_rule": {
      "amount_type": "rebate",
      "amount_flat": null,
      "amount_percent": null,
      "annual_cap": null,
      "lifetime_cap": null,
      "per_unit_rate": null,
      "per_unit_basis": null,
      "min_project_cost": null
    },
    "cap_category": null,
    "resets_annually": false,
    "available_from_year": null,
    "expires_year": null,
    "step_down_schedule": null,
    "claim_timing": null,
    "income_tier": null,
    "income_max_absolute": null,
    "income_max_ami_percent": null,
    "tax_liability_required": false,
    "stackable": true,
    "subsidy_basis_reduction": true,
    "exclusive_with": [],
    "ownership_required": true,
    "primary_residence_required": true,
    "home_type_eligible": [
      "single_family"
    ],
    "equipment_certification": null,
    "contractor_required": true,
    "energy_audit_required": false,
    "program_status": "active",
    "availability_type": null,
    "data_confidence": "medium",
    "last_verified_date": null,
    "geographic_scope": "state",
    "state": "nc",
    "utility_territory": null,
    "source_url": null,
    "citation_chunk_ids": []
  },
  {
    "program_id": "nc-homes-electric_cooking",
    "name": "HOMES Electric Stove, Cook top, Range, or Oven",
    "source_program_id": null,
    "eligible_upgrades": [
      "electric_cooking"
    ],
    "amount_rule": {
      "amount_type": "rebate",
      "amount_flat": null,
      "amount_percent": null,
      "annual_cap": null,
      "lifetime_cap": null,
      "per_unit_rate": null,
      "per_unit_basis": null,
      "min_project_cost": null
    },
    "cap_category": null,
    "resets_annually": false,
    "available_from_year": null,
    "expires_year": null,
    "step_down_schedule": null,
    "claim_timing": null,
    "income_tier": null,
    "income_max_absolute": null,
    "income_max_ami_percent": null,
    "tax_liability_required": false,
    "stackable": true,
    "subsidy_basis_reduction": true,
    "exclusive_with": [],
    "ownership_required": true,
    "primary_residence_required": true,
    "home_type_eligible": [
      "single_family"
    ],
    "equipment_certification": null,
    "contractor_required": true,
    "energy_audit_required": false,
    "program_status": "active",
    "availability_type": null,
    "data_confidence": "medium",
    "last_verified_date": null,
    "geographic_scope": "state",
    "state": "nc",
    "utility_territory": null,
    "source_url": null,
    "citation_chunk_ids": []
  },
  {
    "program_id": "nc-homes-air_sealing",
    "name": "HOMES Air Sealing",
    "source_program_id": null,
    "eligible_upgrades": [
      "air_sealing"
    ],
    "amount_rule": {
      "amount_type": "rebate",
      "amount_flat": null,
      "amount_percent": null,
      "annual_cap": null,
      "lifetime_cap": null,
      "per_unit_rate": null,
      "per_unit_basis": null,
      "min_project_cost": null
    },
    "cap_category": null,
    "resets_annually": false,
    "available_from_year": null,
    "expires_year": null,
    "step_down_schedule": null,
    "claim_timing": null,
    "income_tier": null,
    "income_max_absolute": null,
    "income_max_ami_percent": null,
    "tax_liability_required": false,
    "stackable": true,
    "subsidy_basis_reduction": true,
    "exclusive_with": [],
    "ownership_required": true,
    "primary_residence_required": true,
    "home_type_eligible": [
      "single_family"
    ],
    "equipment_certification": null,
    "contractor_required": true,
    "energy_audit_required": false,
    "program_status": "active",
    "availability_type": null,
    "data_confidence": "medium",
    "last_verified_date": null,
    "geographic_scope": "state",
    "state": "nc",
    "utility_territory": null,
    "source_url": null,
    "citation_chunk_ids": []
  },
  {
    "program_id": "nc-homes-insulation",
    "name": "HOMES Insulation",
    "source_program_id": null,
    "eligible_upgrades": [
      "attic_insulation",
      "duct_sealing"
    ],
    "amount_rule": {
      "amount_type": "rebate",
      "amount_flat": null,
      "amount_percent": null,
      "annual_cap": null,
      "lifetime_cap": null,
      "per_unit_rate": null,
      "per_unit_basis": null,
      "min_project_cost": null
    },
    "cap_category": null,
    "resets_annually": false,
    "available_from_year": null,
    "expires_year": null,
    "step_down_schedule": null,
    "claim_timing": null,
    "income_tier": null,
    "income_max_absolute": null,
    "income_max_ami_percent": null,
    "tax_liability_required": false,
    "stackable": true,
    "subsidy_basis_reduction": true,
    "exclusive_with": [],
    "ownership_required": true,
    "primary_residence_required": true,
    "home_type_eligible": [
      "single_family"
    ],
    "equipment_certification": null,
    "contractor_required": true,
    "energy_audit_required": false,
    "program_status": "active",
    "availability_type": null,
    "data_confidence": "medium",
    "last_verified_date": null,
    "geographic_scope": "state",
    "state": "nc",
    "utility_territory": null,
    "source_url": null,
    "citation_chunk_ids": []
  },
  {
    "program_id": "nc-hear-heat_pump_clothes_dryer",
    "name": "HE AR Electric Heat Pump Clothes Dryer",
    "source_program_id": null,
    "eligible_upgrades": [
      "heat_pump_clothes_dryer"
    ],
    "amount_rule": {
      "amount_type": "rebate",
      "amount_flat": null,
      "amount_percent": null,
      "annual_cap": null,
      "lifetime_cap": null,
      "per_unit_rate": null,
      "per_unit_basis": null,
      "min_project_cost": null
    },
    "cap_category": null,
    "resets_annually": false,
    "available_from_year": null,
    "expires_year": null,
    "step_down_schedule": null,
    "claim_timing": null,
    "income_tier": null,
    "income_max_absolute": null,
    "income_max_ami_percent": null,
    "tax_liability_required": false,
    "stackable": true,
    "subsidy_basis_reduction": true,
    "exclusive_with": [],
    "ownership_required": true,
    "primary_residence_required": true,
    "home_type_eligible": [
      "single_family"
    ],
    "equipment_certification": null,
    "contractor_required": true,
    "energy_audit_required": false,
    "program_status": "active",
    "availability_type": null,
    "data_confidence": "medium",
    "last_verified_date": null,
    "geographic_scope": "state",
    "state": "nc",
    "utility_territory": null,
    "source_url": null,
    "citation_chunk_ids": []
  },
  {
    "program_id": "nc-hear-electric-heat-pump",
    "name": "Electric Heat Pump Rebate (HEAR)",
    "source_program_id": null,
    "eligible_upgrades": [
      "heat_pump"
    ],
    "amount_rule": {
      "amount_type": "rebate",
      "amount_flat": 8000.0,
      "amount_percent": null,
      "annual_cap": null,
      "lifetime_cap": null,
      "per_unit_rate": null,
      "per_unit_basis": null,
      "min_project_cost": null
    },
    "cap_category": null,
    "resets_annually": false,
    "available_from_year": null,
    "expires_year": null,
    "step_down_schedule": null,
    "claim_timing": "point_of_sale",
    "income_tier": "below_80_ami",
    "income_max_absolute": 125000.0,
    "income_max_ami_percent": null,
    "tax_liability_required": false,
    "stackable": true,
    "subsidy_basis_reduction": true,
    "exclusive_with": [],
    "ownership_required": true,
    "primary_residence_required": true,
    "home_type_eligible": [
      "single_family"
    ],
    "equipment_certification": null,
    "contractor_required": true,
    "energy_audit_required": false,
    "program_status": "active",
    "availability_type": null,
    "data_confidence": "high",
    "last_verified_date": null,
    "geographic_scope": "state",
    "state": "nc",
    "utility_territory": null,
    "source_url": null,
    "citation_chunk_ids": []
  },
  {
    "program_id": "nc-hear-electrical-panel",
    "name": "Electrical Panel Rebate (HEAR)",
    "source_program_id": null,
    "eligible_upgrades": [
      "electrical_panel"
    ],
    "amount_rule": {
      "amount_type": "rebate",
      "amount_flat": 4000.0,
      "amount_percent": null,
      "annual_cap": null,
      "lifetime_cap": null,
      "per_unit_rate": null,
      "per_unit_basis": null,
      "min_project_cost": null
    },
    "cap_category": null,
    "resets_annually": false,
    "available_from_year": null,
    "expires_year": null,
    "step_down_schedule": null,
    "claim_timing": "point_of_sale",
    "income_tier": "below_80_ami",
    "income_max_absolute": 125000.0,
    "income_max_ami_percent": null,
    "tax_liability_required": false,
    "stackable": true,
    "subsidy_basis_reduction": true,
    "exclusive_with": [],
    "ownership_required": true,
    "primary_residence_required": true,
    "home_type_eligible": [
      "single_family"
    ],
    "equipment_certification": null,
    "contractor_required": true,
    "energy_audit_required": false,
    "program_status": "active",
    "availability_type": null,
    "data_confidence": "high",
    "last_verified_date": null,
    "geographic_scope": "state",
    "state": "nc",
    "utility_territory": null,
    "source_url": null,
    "citation_chunk_ids": []
  },
  {
    "program_id": "nc-hear-electrical-wiring",
    "name": "Electrical Wiring Rebate (HEAR)",
    "source_program_id": null,
    "eligible_upgrades": [
      "electrical_wiring"
    ],
    "amount_rule": {
      "amount_type": "rebate",
      "amount_flat": 2500.0,
      "amount_percent": null,
      "annual_cap": null,
      "lifetime_cap": null,
      "per_unit_rate": null,
      "per_unit_basis": null,
      "min_project_cost": null
    },
    "cap_category": null,
    "resets_annually": false,
    "available_from_year": null,
    "expires_year": null,
    "step_down_schedule": null,
    "claim_timing": "point_of_sale",
    "income_tier": "below_80_ami",
    "income_max_absolute": 125000.0,
    "income_max_ami_percent": null,
    "tax_liability_required": false,
    "stackable": true,
    "subsidy_basis_reduction": true,
    "exclusive_with": [],
    "ownership_required": true,
    "primary_residence_required": true,
    "home_type_eligible": [
      "single_family"
    ],
    "equipment_certification": null,
    "contractor_required": true,
    "energy_audit_required": false,
    "program_status": "active",
    "availability_type": null,
    "data_confidence": "high",
    "last_verified_date": null,
    "geographic_scope": "state",
    "state": "nc",
    "utility_territory": null,
    "source_url": null,
    "citation_chunk_ids": []
  },
  {
    "program_id": "nc-hear-electric-heat-pump-water-heater",
    "name": "Electric Heat Pump Water Heater Rebate (HEAR)",
    "source_program_id": null,
    "eligible_upgrades": [
      "heat_pump_water_heater"
    ],
    "amount_rule": {
      "amount_type": "rebate",
      "amount_flat": 1600.0,
      "amount_percent": null,
      "annual_cap": null,
      "lifetime_cap": null,
      "per_unit_rate": null,
      "per_unit_basis": null,
      "min_project_cost": null
    },
    "cap_category": null,
    "resets_annually": false,
    "available_from_year": null,
    "expires_year": null,
    "step_down_schedule": null,
    "claim_timing": "point_of_sale",
    "income_tier": "below_80_ami",
    "income_max_absolute": 125000.0,
    "income_max_ami_percent": null,
    "tax_liability_required": false,
    "stackable": true,
    "subsidy_basis_reduction": true,
    "exclusive_with": [],
    "ownership_required": true,
    "primary_residence_required": true,
    "home_type_eligible": [
      "single_family"
    ],
    "equipment_certification": null,
    "contractor_required": true,
    "energy_audit_required": false,
    "program_status": "active",
    "availability_type": null,
    "data_confidence": "high",
    "last_verified_date": null,
    "geographic_scope": "state",
    "state": "nc",
    "utility_territory": null,
    "source_url": null,
    "citation_chunk_ids": []
  },
  {
    "program_id": "nc-hear-electric-range-cooktop",
    "name": "Electric Range/Cooktop Rebate (HEAR)",
    "source_program_id": null,
    "eligible_upgrades": [
      "electric_cooking"
    ],
    "amount_rule": {
      "amount_type": "rebate",
      "amount_flat": 840.0,
      "amount_percent": null,
      "annual_cap": null,
      "lifetime_cap": null,
      "per_unit_rate": null,
      "per_unit_basis": null,
      "min_project_cost": null
    },
    "cap_category": null,
    "resets_annually": false,
    "available_from_year": null,
    "expires_year": null,
    "step_down_schedule": null,
    "claim_timing": "point_of_sale",
    "income_tier": "below_80_ami",
    "income_max_absolute": 125000.0,
    "income_max_ami_percent": null,
    "tax_liability_required": false,
    "stackable": true,
    "subsidy_basis_reduction": true,
    "exclusive_with": [],
    "ownership_required": true,
    "primary_residence_required": true,
    "home_type_eligible": [
      "single_family"
    ],
    "equipment_certification": null,
    "contractor_required": true,
    "energy_audit_required": false,
    "program_status": "active",
    "availability_type": null,
    "data_confidence": "high",
    "last_verified_date": null,
    "geographic_scope": "state",
    "state": "nc",
    "utility_territory": null,
    "source_url": null,
    "citation_chunk_ids": []
  },
  {
    "program_id": "nc-hear-heat-pump-dryer",
    "name": "Heat Pump Dryer Rebate (HEAR)",
    "source_program_id": null,
    "eligible_upgrades": [
      "heat_pump_clothes_dryer"
    ],
    "amount_rule": {
      "amount_type": "rebate",
      "amount_flat": 840.0,
      "amount_percent": null,
      "annual_cap": null,
      "lifetime_cap": null,
      "per_unit_rate": null,
      "per_unit_basis": null,
      "min_project_cost": null
    },
    "cap_category": null,
    "resets_annually": false,
    "available_from_year": null,
    "expires_year": null,
    "step_down_schedule": null,
    "claim_timing": "point_of_sale",
    "income_tier": "below_80_ami",
    "income_max_absolute": 125000.0,
    "income_max_ami_percent": null,
    "tax_liability_required": false,
    "stackable": true,
    "subsidy_basis_reduction": true,
    "exclusive_with": [],
    "ownership_required": true,
    "primary_residence_required": true,
    "home_type_eligible": [
      "single_family"
    ],
    "equipment_certification": null,
    "contractor_required": true,
    "energy_audit_required": false,
    "program_status": "active",
    "availability_type": null,
    "data_confidence": "high",
    "last_verified_date": null,
    "geographic_scope": "state",
    "state": "nc",
    "utility_territory": null,
    "source_url": null,
    "citation_chunk_ids": []
  },
  {
    "program_id": "nc-hear-attic-insulation",
    "name": "Insulation Rebate (HEAR)",
    "source_program_id": "nc-hear",
    "cap_category": null,
    "resets_annually": false,
    "available_from_year": null,
    "expires_year": null,
    "step_down_schedule": null,
    "claim_timing": "point_of_sale",
    "income_tier": "below_80_ami",
    "income_max_absolute": 125000.0,
    "income_max_ami_percent": null,
    "tax_liability_required": false,
    "stackable": true,
    "subsidy_basis_reduction": true,
    "exclusive_with": [],
    "ownership_required": true,
    "primary_residence_required": true,
    "home_type_eligible": [
      "single_family"
    ],
    "equipment_certification": null,
    "contractor_required": true,
    "energy_audit_required": false,
    "program_status": "active",
    "availability_type": null,
    "data_confidence": "high",
    "last_verified_date": null,
    "geographic_scope": "state",
    "state": "nc",
    "utility_territory": null,
    "source_url": null,
    "citation_chunk_ids": [],
    "eligible_upgrades": [
      "attic_insulation"
    ],
    "amount_rule": {
      "amount_type": "rebate",
      "amount_flat": 1600.0,
      "amount_percent": null,
      "annual_cap": null,
      "lifetime_cap": null,
      "per_unit_rate": null,
      "per_unit_basis": null,
      "min_project_cost": null
    },
    "program_notes": "Part of the $2,500 HEAR weatherization combined cap across insulation, air sealing, and duct sealing. Total rebate across all measures is capped at $2,500."
  },
  {
    "program_id": "nc-hear-air-sealing",
    "name": "Air Sealing Rebate (HEAR)",
    "source_program_id": "nc-hear",
    "cap_category": null,
    "resets_annually": false,
    "available_from_year": null,
    "expires_year": null,
    "step_down_schedule": null,
    "claim_timing": "point_of_sale",
    "income_tier": "below_80_ami",
    "income_max_absolute": 125000.0,
    "income_max_ami_percent": null,
    "tax_liability_required": false,
    "stackable": true,
    "subsidy_basis_reduction": true,
    "exclusive_with": [],
    "ownership_required": true,
    "primary_residence_required": true,
    "home_type_eligible": [
      "single_family"
    ],
    "equipment_certification": null,
    "contractor_required": true,
    "energy_audit_required": false,
    "program_status": "active",
    "availability_type": null,
    "data_confidence": "high",
    "last_verified_date": null,
    "geographic_scope": "state",
    "state": "nc",
    "utility_territory": null,
    "source_url": null,
    "citation_chunk_ids": [],
    "eligible_upgrades": [
      "air_sealing"
    ],
    "amount_rule": {
      "amount_type": "rebate",
      "amount_flat": 900.0,
      "amount_percent": null,
      "annual_cap": null,
      "lifetime_cap": null,
      "per_unit_rate": null,
      "per_unit_basis": null,
      "min_project_cost": null
    },
    "program_notes": "Part of the $2,500 HEAR weatherization combined cap across insulation, air sealing, and duct sealing. Total rebate across all measures is capped at $2,500."
  },
  {
    "program_id": "nc-smart-saver-attic-insulation",
    "name": "Smart $aver Attic Insulation Rebate",
    "source_program_id": "nc-smart-saver",
    "cap_category": null,
    "resets_annually": false,
    "available_from_year": null,
    "expires_year": null,
    "step_down_schedule": null,
    "claim_timing": "point_of_sale",
    "income_tier": null,
    "income_max_absolute": null,
    "income_max_ami_percent": null,
    "tax_liability_required": false,
    "stackable": true,
    "subsidy_basis_reduction": true,
    "exclusive_with": [],
    "ownership_required": true,
    "primary_residence_required": true,
    "home_type_eligible": [
      "single_family"
    ],
    "equipment_certification": null,
    "contractor_required": true,
    "energy_audit_required": false,
    "program_status": "active",
    "availability_type": null,
    "data_confidence": "high",
    "last_verified_date": null,
    "geographic_scope": "state",
    "state": "nc",
    "utility_territory": "Duke Energy Progress",
    "source_url": null,
    "citation_chunk_ids": [],
    "utility_notes": "Also available via Dominion Energy North Carolina \u2014 check with your utility.",
    "eligible_upgrades": [
      "attic_insulation"
    ],
    "amount_rule": {
      "amount_type": "rebate",
      "amount_flat": 350.0,
      "amount_percent": null,
      "annual_cap": null,
      "lifetime_cap": null,
      "per_unit_rate": null,
      "per_unit_basis": null,
      "min_project_cost": null
    },
    "program_notes": "Part of the $500 Smart $aver combined rebate for attic insulation and air sealing. Total across both measures is $500."
  },
  {
    "program_id": "nc-smart-saver-air-sealing",
    "name": "Smart $aver Air Sealing Rebate",
    "source_program_id": "nc-smart-saver",
    "cap_category": null,
    "resets_annually": false,
    "available_from_year": null,
    "expires_year": null,
    "step_down_schedule": null,
    "claim_timing": "point_of_sale",
    "income_tier": null,
    "income_max_absolute": null,
    "income_max_ami_percent": null,
    "tax_liability_required": false,
    "stackable": true,
    "subsidy_basis_reduction": true,
    "exclusive_with": [],
    "ownership_required": true,
    "primary_residence_required": true,
    "home_type_eligible": [
      "single_family"
    ],
    "equipment_certification": null,
    "contractor_required": true,
    "energy_audit_required": false,
    "program_status": "active",
    "availability_type": null,
    "data_confidence": "high",
    "last_verified_date": null,
    "geographic_scope": "state",
    "state": "nc",
    "utility_territory": "Duke Energy Progress",
    "source_url": null,
    "citation_chunk_ids": [],
    "utility_notes": "Also available via Dominion Energy North Carolina \u2014 check with your utility.",
    "eligible_upgrades": [
      "air_sealing"
    ],
    "amount_rule": {
      "amount_type": "rebate",
      "amount_flat": 150.0,
      "amount_percent": null,
      "annual_cap": null,
      "lifetime_cap": null,
      "per_unit_rate": null,
      "per_unit_basis": null,
      "min_project_cost": null
    },
    "program_notes": "Part of the $500 Smart $aver combined rebate for attic insulation and air sealing. Total across both measures is $500."
  }
]